peft/__init__.py
peft/import_utils.py
peft/mapping.py
peft/peft_model.py
peft/tuners/__init__.py
peft/tuners/adalora.py
peft/tuners/adaption_prompt.py
peft/tuners/lora.py
peft/tuners/p_tuning.py
peft/tuners/prefix_tuning.py
peft/tuners/prompt_tuning.py
peft/utils/__init__.py
peft/utils/config.py
peft/utils/other.py
peft/utils/save_and_load.py
vfpeft-0.4.0.dev0.dist-info/LICENSE
vfpeft-0.4.0.dev0.dist-info/METADATA
vfpeft-0.4.0.dev0.dist-info/WHEEL
vfpeft-0.4.0.dev0.dist-info/top_level.txt
vfpeft-0.4.0.dev0.dist-info/RECORD
