Metadata-Version: 2.1
Name: vfpeft
Version: 0.4.0.dev0
Summary: Parameter-Efficient Fine-Tuning (PEFT)
Home-page: https://github.com/alicabukel/vfpeft
Author: overenginar
Author-email: alicabukel@proton.me
License: Apache
Keywords: deep learning
Classifier: Development Status :: 5 - Production/Stable
Classifier: Intended Audience :: Developers
Classifier: Intended Audience :: Education
Classifier: Intended Audience :: Science/Research
Classifier: License :: OSI Approved :: Apache Software License
Classifier: Operating System :: OS Independent
Classifier: Programming Language :: Python :: 3
Classifier: Programming Language :: Python :: 3.7
Classifier: Topic :: Scientific/Engineering :: Artificial Intelligence
Requires-Python: >=3.7.0
License-File: LICENSE
Requires-Dist: numpy (>=1.17)
Requires-Dist: packaging (>=20.0)
Requires-Dist: psutil
Requires-Dist: pyyaml
Requires-Dist: torch (>=1.13.0)
Requires-Dist: transformers
Requires-Dist: accelerate
Provides-Extra: dev
Requires-Dist: black (~=22.0) ; extra == 'dev'
Requires-Dist: ruff (>=0.0.241) ; extra == 'dev'
Requires-Dist: urllib3 (<=2.0.0) ; extra == 'dev'
Requires-Dist: hf-doc-builder ; extra == 'dev'
Provides-Extra: docs_specific
Requires-Dist: hf-doc-builder ; extra == 'docs_specific'
Provides-Extra: quality
Requires-Dist: black (~=22.0) ; extra == 'quality'
Requires-Dist: ruff (>=0.0.241) ; extra == 'quality'
Requires-Dist: urllib3 (<=2.0.0) ; extra == 'quality'
Provides-Extra: test
Requires-Dist: black (~=22.0) ; extra == 'test'
Requires-Dist: ruff (>=0.0.241) ; extra == 'test'
Requires-Dist: urllib3 (<=2.0.0) ; extra == 'test'
Requires-Dist: hf-doc-builder ; extra == 'test'
Requires-Dist: pytest ; extra == 'test'
Requires-Dist: pytest-xdist ; extra == 'test'
Requires-Dist: parameterized ; extra == 'test'
Requires-Dist: datasets ; extra == 'test'
